setup.py
fidelity/__init__.py
fidelity/converter.py
fidelity.egg-info/PKG-INFO
fidelity.egg-info/SOURCES.txt
fidelity.egg-info/dependency_links.txt
fidelity.egg-info/top_level.txt