Metadata-Version: 1.0
Name: fidelity
Version: 0.1
Summary: Library for transcribing Tigrinya in ASCII
Home-page: http://github.com/morrisalp/fidelity
Author: Morris Alper
Author-email: morrisalp@gmail.com
License: CC
Platform: UNKNOWN
